{
  "$schema": "https://mintlify.com/schema.json",
  "name": "Throxy API",
  "logo": {
    "dark": "/logo/dark.svg",
    "light": "/logo/light.svg"
  },
  "favicon": "/favicon.svg",
  "colors": {
    "primary": "#0D9373",
    "light": "#07C983",
    "dark": "#0D9373",
    "anchors": {
      "from": "#0D9373",
      "to": "#07C983"
    }
  },
  "topbarLinks": [
    {
      "name": "Get help",
      "url": "https://cal.com/arnau-ayerbe/15min"
    }
  ],
  "tabs": [
    {
      "name": "API Reference",
      "url": "api-reference"
    }
  ],
  "anchors": [

  ],
  "navigation": [
    {
      "group": "throxy",
      "pages": [
        "introduction"
      ]
    },
    {
      "group": "API Documentation",
      "pages": [
        "/introduction"
      ]
    },
    {
      "group": "Lead Finding API",
      "pages": [
        "/lead-finding/introduction",
        "/lead-finding/get-all-jobs",
        "/lead-finding/get-job-details",
        "/lead-finding/schedule-job"
      ]
    }
  ],
  "footerSocials": {
    "linkedin": "https://linkedin.com/company/throxy"
  }
}
